nameko_salesforce/__init__.py
nameko_salesforce/constants.py
nameko_salesforce/api/__init__.py
nameko_salesforce/api/client.py
nameko_salesforce/api/dependency.py
nameko_salesforce/api/push_topics.py
nameko_salesforce/streaming/__init__.py
nameko_salesforce/streaming/channels.py
nameko_salesforce/streaming/client.py
nameko_salesforce-1.2.0.dist-info/METADATA
nameko_salesforce-1.2.0.dist-info/RECORD
nameko_salesforce-1.2.0.dist-info/WHEEL
nameko_salesforce-1.2.0.dist-info/top_level.txt
nameko_salesforce-1.2.0.dist-info/zip-safe
tests/__init__.py
tests/conftest.py
tests/api/__init__.py
tests/api/test_client.py
tests/api/test_dependency.py
tests/api/test_push_topics.py
tests/streaming/__init__.py
tests/streaming/conftest.py
tests/streaming/test_end_to_end.py
tests/streaming/test_unit.py
