Metadata-Version: 2.1
Name: nameko-salesforce
Version: 1.2.0
Summary: Nameko extension for easy communication with Salesforce (Including Streaming API)
Home-page: http://github.com/Overseas-Student-Living/nameko-salesforce
Author: Student.com
Author-email: wearehiring@student.com
License: Apache License, Version 2.0
Platform: UNKNOWN
Classifier: Programming Language :: Python
Classifier: Operating System :: MacOS :: MacOS X
Classifier: Operating System :: POSIX
Classifier: Programming Language :: Python :: 3
Classifier: Programming Language :: Python :: 3.4
Classifier: Programming Language :: Python :: 3.5
Classifier: Programming Language :: Python :: 3.6
Classifier: Topic :: Internet
Classifier: Topic :: Software Development :: Libraries :: Python Modules
Classifier: Intended Audience :: Developers
Provides-Extra: docs
Provides-Extra: dev
Requires-Dist: cachetools (==2.0.0)
Requires-Dist: nameko (>=2.5.1)
Requires-Dist: nameko-bayeux-client (==1.0.0)
Requires-Dist: redis (==2.10.5)
Requires-Dist: simple-salesforce (==0.72.2)
Provides-Extra: dev
Requires-Dist: coverage (==4.3.4); extra == 'dev'
Requires-Dist: flake8 (==3.3.0); extra == 'dev'
Requires-Dist: pylint (==1.8.2); extra == 'dev'
Requires-Dist: pytest (==3.0.6); extra == 'dev'
Requires-Dist: requests-mock (==1.3.0); extra == 'dev'
Provides-Extra: docs
Requires-Dist: Sphinx (==1.6.2); extra == 'docs'
Requires-Dist: sphinx-rtd-theme (==0.2.4); extra == 'docs'
